{
  "plant": "WG Wellington square",
  "last_updated": "2026-04-12 01:51 SAST",
  "date": "2026-04-12",
  "total_kwh": 0.0,
  "last_hour": 0,
  "status": "ok",
  "alerts": {
    "offline": false,
    "pace_low": false,
    "total_low": false
  },
  "today": {
    "hourly_pv": [
      0.0,
      0.0,
      0.0,
      0.0,
      0.0,
      0.0,
      0.0,
      0.0,
      0.0,
      0.0,
      0.0,
      0.0,
      0.0,
      0.0,
      0.0,
      0.0,
      0.0,
      0.0,
      0.0,
      0.0,
      0.0,
      0.0,
      0.0,
      0.0
    ],
    "irradiation": [
      0,
      0,
      0,
      0,
      0,
      0,
      0,
      0,
      23.0,
      60.0,
      79.0,
      100.0,
      121.0,
      170.0,
      110.0,
      80.0,
      71.0,
      48.0,
      14.0,
      0,
      0,
      0,
      0,
      0
    ]
  },
  "hourly_pv": [
    0.0,
    0.0,
    0.0,
    0.0,
    0.0,
    0.0,
    0.0,
    0.0,
    0.0,
    0.0,
    0.0,
    0.0,
    0.0,
    0.0,
    0.0,
    0.0,
    0.0,
    0.0,
    0.0,
    0.0,
    0.0,
    0.0,
    0.0,
    0.0
  ],
  "irradiation": [
    0,
    0,
    0,
    0,
    0,
    0,
    0,
    0,
    23.0,
    60.0,
    79.0,
    100.0,
    121.0,
    170.0,
    110.0,
    80.0,
    71.0,
    48.0,
    14.0,
    0,
    0,
    0,
    0,
    0
  ],
  "stats_30day": {
    "hourly_avg": [
      0.0,
      0.0,
      0.0,
      0.0,
      0.0,
      0.0,
      0.0,
      0.37,
      10.44,
      29.41,
      39.08,
      57.6,
      56.24,
      50.69,
      37.63,
      36.76,
      35.14,
      12.08,
      0.75,
      0.0,
      0.0,
      0.0,
      0.0,
      0.0
    ],
    "hourly_min": [
      0,
      0,
      0,
      0,
      0,
      0,
      0,
      0.07,
      1.74,
      5.96,
      4.56,
      8.35,
      8.24,
      7.99,
      13.33,
      11.03,
      6.05,
      2.73,
      0.06,
      0,
      0,
      0,
      0,
      0
    ],
    "hourly_max": [
      0.0,
      0.0,
      0.0,
      0.0,
      0.0,
      0.0,
      0.0,
      0.97,
      21.0,
      50.95,
      76.22,
      109.76,
      110.7,
      96.98,
      89.96,
      80.57,
      62.77,
      23.6,
      2.21,
      0.0,
      0.0,
      0.0,
      0.0,
      0.0
    ],
    "hourly_p10": [
      0.0,
      0.0,
      0.0,
      0.0,
      0.0,
      0.0,
      0.0,
      0.06,
      1.57,
      7.43,
      14.05,
      22.11,
      13.07,
      12.17,
      14.94,
      11.86,
      8.32,
      3.25,
      0.0,
      0.0,
      0.0,
      0.0,
      0.0,
      0.0
    ],
    "hourly_p25": [
      0.0,
      0.0,
      0.0,
      0.0,
      0.0,
      0.0,
      0.0,
      0.1,
      3.04,
      16.39,
      19.17,
      32.17,
      30.07,
      24.19,
      20.28,
      14.95,
      12.91,
      6.69,
      0.07,
      0.0,
      0.0,
      0.0,
      0.0,
      0.0
    ],
    "hourly_p75": [
      0.0,
      0.0,
      0.0,
      0.0,
      0.0,
      0.0,
      0.0,
      0.62,
      16.5,
      48.08,
      63.39,
      82.05,
      89.77,
      82.68,
      37.21,
      64.31,
      53.99,
      18.18,
      1.58,
      0.0,
      0.0,
      0.0,
      0.0,
      0.0
    ],
    "hourly_p90": [
      0.0,
      0.0,
      0.0,
      0.0,
      0.0,
      0.0,
      0.0,
      0.92,
      17.63,
      50.95,
      74.25,
      91.47,
      98.07,
      92.92,
      86.66,
      75.7,
      58.02,
      21.17,
      2.03,
      0.0,
      0.0,
      0.0,
      0.0,
      0.0
    ],
    "hourly_irrad_avg": [
      0.0,
      0.0,
      0.0,
      0.0,
      0.0,
      0.0,
      0.0,
      1.4,
      72.7,
      217.8,
      353.5,
      460.9,
      535.3,
      567.1,
      547.7,
      478.8,
      350.2,
      202.3,
      67.4,
      2.1,
      0.0,
      0.0,
      0.0,
      0.0
    ],
    "daily_min": 110.5,
    "daily_max": 671.7,
    "daily_avg": 366.2,
    "sample_days": 10
  },
  "history": {
    "2026-04-02": {
      "total_kwh": 296.81,
      "hourly": [
        0.0,
        0.0,
        0.0,
        0.0,
        0.0,
        0.0,
        0.0,
        0.0,
        0.0,
        19.16,
        41.67,
        51.83,
        32.28,
        48.0,
        27.3,
        27.92,
        34.9,
        11.74,
        2.01,
        0.0,
        0.0,
        0.0,
        0.0,
        0.0
      ],
      "irradiation": [
        0,
        0,
        0,
        0,
        0,
        0,
        0,
        2.0,
        67.0,
        190.0,
        252.0,
        306.0,
        413.0,
        248.0,
        291.0,
        365.0,
        260.0,
        126.0,
        45.0,
        3.0,
        0,
        0,
        0,
        0
      ],
      "last_updated": "2026-04-02 23:52 SAST",
      "last_hour": 18
    },
    "2026-04-03": {
      "total_kwh": 110.47,
      "hourly": [
        0.0,
        0.0,
        0.0,
        0.0,
        0.0,
        0.0,
        0.0,
        0.09,
        1.74,
        5.96,
        4.56,
        8.35,
        13.61,
        7.99,
        33.59,
        16.04,
        8.57,
        9.97,
        0.0,
        0.0,
        0.0,
        0.0,
        0.0,
        0.0
      ],
      "irradiation": [
        0,
        0,
        0,
        0,
        0,
        0,
        0,
        1.0,
        50.0,
        149.0,
        152.0,
        122.0,
        89.0,
        111.0,
        110.0,
        73.0,
        54.0,
        30.0,
        11.0,
        1.0,
        0,
        0,
        0,
        0
      ],
      "last_updated": "2026-04-03 23:49 SAST",
      "last_hour": 17
    },
    "2026-04-04": {
      "total_kwh": 345.5,
      "hourly": [
        0.0,
        0.0,
        0.0,
        0.0,
        0.0,
        0.0,
        0.0,
        0.97,
        5.44,
        44.71,
        26.96,
        78.45,
        110.7,
        19.51,
        15.12,
        34.8,
        6.05,
        2.73,
        0.06,
        0.0,
        0.0,
        0.0,
        0.0,
        0.0
      ],
      "irradiation": [
        0,
        0,
        0,
        0,
        0,
        0,
        0,
        1.0,
        75.0,
        217.0,
        426.0,
        625.0,
        725.0,
        742.0,
        709.0,
        601.0,
        404.0,
        242.0,
        76.0,
        3.0,
        0,
        0,
        0,
        0
      ],
      "last_updated": "2026-04-04 23:44 SAST",
      "last_hour": 18
    },
    "2026-04-05": {
      "total_kwh": 223.1,
      "hourly": [
        0.0,
        0.0,
        0.0,
        0.0,
        0.0,
        0.0,
        0.0,
        0.07,
        2.24,
        7.59,
        15.11,
        28.4,
        49.18,
        38.21,
        18.09,
        11.95,
        45.18,
        6.99,
        0.09,
        0.0,
        0.0,
        0.0,
        0.0,
        0.0
      ],
      "irradiation": [
        0,
        0,
        0,
        0,
        0,
        0,
        0,
        1.0,
        66.0,
        210.0,
        349.0,
        460.0,
        433.0,
        557.0,
        630.0,
        515.0,
        347.0,
        194.0,
        64.0,
        3.0,
        0,
        0,
        0,
        0
      ],
      "last_updated": "2026-04-05 23:46 SAST",
      "last_hour": 18
    },
    "2026-04-06": {
      "total_kwh": 425.46,
      "hourly": [
        0.0,
        0.0,
        0.0,
        0.0,
        0.0,
        0.0,
        0.0,
        0.91,
        17.26,
        50.95,
        76.22,
        109.76,
        29.34,
        60.09,
        38.42,
        14.59,
        20.55,
        6.59,
        0.78,
        0.0,
        0.0,
        0.0,
        0.0,
        0.0
      ],
      "irradiation": [
        0,
        0,
        0,
        0,
        0,
        0,
        0,
        2.0,
        97.0,
        304.0,
        480.0,
        571.0,
        659.0,
        687.0,
        630.0,
        527.0,
        414.0,
        239.0,
        83.0,
        3.0,
        0,
        0,
        0,
        0
      ],
      "last_updated": "2026-04-06 23:51 SAST",
      "last_hour": 18
    },
    "2026-04-07": {
      "total_kwh": 671.66,
      "hourly": [
        0.0,
        0.0,
        0.0,
        0.0,
        0.0,
        0.0,
        0.0,
        0.68,
        16.73,
        50.95,
        74.03,
        89.44,
        96.67,
        96.98,
        89.96,
        75.16,
        55.25,
        23.6,
        2.21,
        0.0,
        0.0,
        0.0,
        0.0,
        0.0
      ],
      "irradiation": [
        0,
        0,
        0,
        0,
        0,
        0,
        0,
        2.0,
        104.0,
        306.0,
        497.0,
        649.0,
        745.0,
        780.0,
        748.0,
        653.0,
        502.0,
        312.0,
        110.0,
        3.0,
        0,
        0,
        0,
        0
      ],
      "last_updated": "2026-04-07 23:57 SAST",
      "last_hour": 18
    },
    "2026-04-08": {
      "total_kwh": 581.92,
      "hourly": [
        0.0,
        0.0,
        0.0,
        0.0,
        0.0,
        0.0,
        0.0,
        0.44,
        15.81,
        49.2,
        70.63,
        83.25,
        90.47,
        90.21,
        27.3,
        80.57,
        57.49,
        16.12,
        0.43,
        0.0,
        0.0,
        0.0,
        0.0,
        0.0
      ],
      "irradiation": [
        0,
        0,
        0,
        0,
        0,
        0,
        0,
        2.0,
        103.0,
        303.0,
        491.0,
        640.0,
        735.0,
        763.0,
        721.0,
        634.0,
        476.0,
        243.0,
        89.0,
        2.0,
        0,
        0,
        0,
        0
      ],
      "last_updated": "2026-04-08 23:58 SAST",
      "last_hour": 18
    },
    "2026-04-09": {
      "total_kwh": 536.91,
      "hourly": [
        0.0,
        0.0,
        0.0,
        0.0,
        0.0,
        0.0,
        0.0,
        0.16,
        14.69,
        31.5,
        35.28,
        43.49,
        87.68,
        92.47,
        86.29,
        74.14,
        50.22,
        20.9,
        0.09,
        0.0,
        0.0,
        0.0,
        0.0,
        0.0
      ],
      "irradiation": [
        0,
        0,
        0,
        0,
        0,
        0,
        0,
        1.0,
        65.0,
        230.0,
        410.0,
        519.0,
        663.0,
        713.0,
        669.0,
        591.0,
        462.0,
        292.0,
        99.0,
        2.0,
        0,
        0,
        0,
        0
      ],
      "last_updated": "2026-04-09 23:57 SAST",
      "last_hour": 18
    },
    "2026-04-10": {
      "total_kwh": 345.34,
      "hourly": [
        0.0,
        0.0,
        0.0,
        0.0,
        0.0,
        0.0,
        0.0,
        0.12,
        21.0,
        18.32,
        29.75,
        59.43,
        44.25,
        40.77,
        26.86,
        21.36,
        62.77,
        18.87,
        1.84,
        0.0,
        0.0,
        0.0,
        0.0,
        0.0
      ],
      "irradiation": [
        0,
        0,
        0,
        0,
        0,
        0,
        0,
        1.0,
        61.0,
        158.0,
        261.0,
        417.0,
        542.0,
        703.0,
        684.0,
        595.0,
        421.0,
        261.0,
        72.0,
        1.0,
        0,
        0,
        0,
        0
      ],
      "last_updated": "2026-04-10 23:54 SAST",
      "last_hour": 18
    },
    "2026-04-11": {
      "total_kwh": 124.65,
      "hourly": [
        0.0,
        0.0,
        0.0,
        0.0,
        0.0,
        0.0,
        0.0,
        0.27,
        9.5,
        15.75,
        16.58,
        23.64,
        8.24,
        12.63,
        13.33,
        11.03,
        10.37,
        3.31,
        0.0,
        0.0,
        0.0,
        0.0,
        0.0,
        0.0
      ],
      "irradiation": [
        0,
        0,
        0,
        0,
        0,
        0,
        0,
        1.0,
        39.0,
        111.0,
        217.0,
        300.0,
        349.0,
        367.0,
        285.0,
        234.0,
        162.0,
        84.0,
        25.0,
        0,
        0,
        0,
        0,
        0
      ],
      "last_updated": "2026-04-11 23:48 SAST",
      "last_hour": 17
    },
    "2026-04-12": {
      "total_kwh": 0.0,
      "hourly": [
        0.0,
        0.0,
        0.0,
        0.0,
        0.0,
        0.0,
        0.0,
        0.0,
        0.0,
        0.0,
        0.0,
        0.0,
        0.0,
        0.0,
        0.0,
        0.0,
        0.0,
        0.0,
        0.0,
        0.0,
        0.0,
        0.0,
        0.0,
        0.0
      ],
      "irradiation": [
        0,
        0,
        0,
        0,
        0,
        0,
        0,
        0,
        23.0,
        60.0,
        79.0,
        100.0,
        121.0,
        170.0,
        110.0,
        80.0,
        71.0,
        48.0,
        14.0,
        0,
        0,
        0,
        0,
        0
      ],
      "last_updated": "2026-04-12 01:51 SAST",
      "last_hour": 0
    }
  },
  "thresholds": {
    "daily_avg": 366.2,
    "daily_min": 110.5,
    "pace_threshold_pct": 0.3,
    "sample_days": 10,
    "min_history_days": 7
  },
  "debug": {
    "reason": "nighttime",
    "sample_days": 10
  }
}