{
  "plant": "Aurora",
  "last_updated": "2026-04-06 01:49 SAST",
  "date": "2026-04-06",
  "total_kwh": 0.0,
  "last_hour": 0,
  "status": "ok",
  "alerts": {
    "offline": false,
    "pace_low": false,
    "total_low": false
  },
  "today": {
    "hourly_pv": [
      0.0,
      0.0,
      0.0,
      0.0,
      0.0,
      0.0,
      0.0,
      0.0,
      0.0,
      0.0,
      0.0,
      0.0,
      0.0,
      0.0,
      0.0,
      0.0,
      0.0,
      0.0,
      0.0,
      0.0,
      0.0,
      0.0,
      0.0,
      0.0
    ],
    "irradiation": [
      0,
      0,
      0,
      0,
      0,
      0,
      0,
      8.0,
      140.0,
      342.0,
      508.0,
      618.0,
      647.0,
      745.0,
      726.0,
      622.0,
      467.0,
      271.0,
      74.0,
      0,
      0,
      0,
      0,
      0
    ]
  },
  "hourly_pv": [
    0.0,
    0.0,
    0.0,
    0.0,
    0.0,
    0.0,
    0.0,
    0.0,
    0.0,
    0.0,
    0.0,
    0.0,
    0.0,
    0.0,
    0.0,
    0.0,
    0.0,
    0.0,
    0.0,
    0.0,
    0.0,
    0.0,
    0.0,
    0.0
  ],
  "irradiation": [
    0,
    0,
    0,
    0,
    0,
    0,
    0,
    8.0,
    140.0,
    342.0,
    508.0,
    618.0,
    647.0,
    745.0,
    726.0,
    622.0,
    467.0,
    271.0,
    74.0,
    0,
    0,
    0,
    0,
    0
  ],
  "stats_30day": {
    "hourly_avg": [
      0.0,
      0.0,
      0.0,
      0.0,
      0.0,
      0.0,
      0.0,
      1.08,
      22.35,
      28.14,
      60.02,
      51.2,
      53.87,
      74.0,
      56.54,
      44.29,
      24.91,
      9.22,
      0.04,
      0.0,
      0.0,
      0.0,
      0.0,
      0.0
    ],
    "hourly_min": [
      0,
      0,
      0,
      0,
      0,
      0,
      0,
      0.35,
      7.05,
      18.61,
      26.1,
      38.0,
      27.27,
      41.13,
      37.24,
      22.52,
      11.08,
      4.24,
      0.16,
      0,
      0,
      0,
      0,
      0
    ],
    "hourly_max": [
      0.0,
      0.0,
      0.0,
      0.0,
      0.0,
      0.0,
      0.0,
      3.27,
      47.05,
      34.24,
      97.5,
      75.13,
      78.51,
      100.79,
      78.33,
      65.95,
      42.46,
      17.3,
      0.16,
      0.0,
      0.0,
      0.0,
      0.0,
      0.0
    ],
    "hourly_p10": [
      0.0,
      0.0,
      0.0,
      0.0,
      0.0,
      0.0,
      0.0,
      0.11,
      9.7,
      21.67,
      32.05,
      40.24,
      30.92,
      47.99,
      40.31,
      22.96,
      12.07,
      4.84,
      0.0,
      0.0,
      0.0,
      0.0,
      0.0,
      0.0
    ],
    "hourly_p25": [
      0.0,
      0.0,
      0.0,
      0.0,
      0.0,
      0.0,
      0.0,
      0.26,
      13.68,
      26.27,
      40.97,
      43.61,
      36.39,
      58.28,
      44.92,
      23.62,
      13.55,
      5.75,
      0.0,
      0.0,
      0.0,
      0.0,
      0.0,
      0.0
    ],
    "hourly_p75": [
      0.0,
      0.0,
      0.0,
      0.0,
      0.0,
      0.0,
      0.0,
      1.36,
      26.31,
      31.71,
      77.3,
      53.44,
      72.34,
      92.76,
      66.91,
      65.03,
      34.41,
      11.15,
      0.04,
      0.0,
      0.0,
      0.0,
      0.0,
      0.0
    ],
    "hourly_p90": [
      0.0,
      0.0,
      0.0,
      0.0,
      0.0,
      0.0,
      0.0,
      2.51,
      38.76,
      33.23,
      89.42,
      66.45,
      76.04,
      97.58,
      73.76,
      65.58,
      39.24,
      14.84,
      0.11,
      0.0,
      0.0,
      0.0,
      0.0,
      0.0
    ],
    "hourly_irrad_avg": [
      0.0,
      0.0,
      0.0,
      0.0,
      0.0,
      0.0,
      0.0,
      6.2,
      92.8,
      239.8,
      391.5,
      509.2,
      532.0,
      540.2,
      501.5,
      447.5,
      328.5,
      160.2,
      48.2,
      0.2,
      0.0,
      0.0,
      0.0,
      0.0
    ],
    "daily_min": 366.3,
    "daily_max": 499.6,
    "daily_avg": 425.7,
    "sample_days": 4
  },
  "history": {
    "2026-04-02": {
      "total_kwh": 386.76,
      "hourly": [
        0.0,
        0.0,
        0.0,
        0.0,
        0.0,
        0.0,
        0.0,
        0.35,
        7.05,
        18.61,
        97.5,
        38.0,
        27.27,
        100.79,
        37.24,
        23.98,
        31.73,
        4.24,
        0.0,
        0.0,
        0.0,
        0.0,
        0.0,
        0.0
      ],
      "irradiation": [
        0,
        0,
        0,
        0,
        0,
        0,
        0,
        4.0,
        67.0,
        195.0,
        371.0,
        548.0,
        580.0,
        584.0,
        539.0,
        548.0,
        404.0,
        194.0,
        69.0,
        1.0,
        0,
        0,
        0,
        0
      ],
      "last_updated": "2026-04-02 23:52 SAST",
      "last_hour": 17
    },
    "2026-04-03": {
      "total_kwh": 366.27,
      "hourly": [
        0.0,
        0.0,
        0.0,
        0.0,
        0.0,
        0.0,
        0.0,
        3.27,
        19.4,
        28.82,
        70.56,
        45.48,
        70.28,
        41.13,
        47.48,
        22.52,
        11.08,
        6.25,
        0.0,
        0.0,
        0.0,
        0.0,
        0.0,
        0.0
      ],
      "irradiation": [
        0,
        0,
        0,
        0,
        0,
        0,
        0,
        8.0,
        123.0,
        323.0,
        462.0,
        468.0,
        370.0,
        318.0,
        269.0,
        318.0,
        181.0,
        66.0,
        17.0,
        0,
        0,
        0,
        0,
        0
      ],
      "last_updated": "2026-04-03 23:49 SAST",
      "last_hour": 17
    },
    "2026-04-04": {
      "total_kwh": 499.6,
      "hourly": [
        0.0,
        0.0,
        0.0,
        0.0,
        0.0,
        0.0,
        0.0,
        0.0,
        47.05,
        34.24,
        45.92,
        75.13,
        39.43,
        90.08,
        78.33,
        65.95,
        14.37,
        9.1,
        0.0,
        0.0,
        0.0,
        0.0,
        0.0,
        0.0
      ],
      "irradiation": [
        0,
        0,
        0,
        0,
        0,
        0,
        0,
        6.0,
        91.0,
        257.0,
        440.0,
        626.0,
        717.0,
        743.0,
        727.0,
        597.0,
        395.0,
        208.0,
        51.0,
        0,
        0,
        0,
        0,
        0
      ],
      "last_updated": "2026-04-04 23:44 SAST",
      "last_hour": 17
    },
    "2026-04-05": {
      "total_kwh": 450.05,
      "hourly": [
        0.0,
        0.0,
        0.0,
        0.0,
        0.0,
        0.0,
        0.0,
        0.72,
        15.89,
        30.87,
        26.1,
        46.21,
        78.51,
        64.0,
        63.11,
        64.72,
        42.46,
        17.3,
        0.16,
        0.0,
        0.0,
        0.0,
        0.0,
        0.0
      ],
      "irradiation": [
        0,
        0,
        0,
        0,
        0,
        0,
        0,
        7.0,
        90.0,
        184.0,
        293.0,
        395.0,
        461.0,
        516.0,
        471.0,
        327.0,
        334.0,
        173.0,
        56.0,
        0,
        0,
        0,
        0,
        0
      ],
      "last_updated": "2026-04-05 23:46 SAST",
      "last_hour": 18
    },
    "2026-04-06": {
      "total_kwh": 0.0,
      "hourly": [
        0.0,
        0.0,
        0.0,
        0.0,
        0.0,
        0.0,
        0.0,
        0.0,
        0.0,
        0.0,
        0.0,
        0.0,
        0.0,
        0.0,
        0.0,
        0.0,
        0.0,
        0.0,
        0.0,
        0.0,
        0.0,
        0.0,
        0.0,
        0.0
      ],
      "irradiation": [
        0,
        0,
        0,
        0,
        0,
        0,
        0,
        8.0,
        140.0,
        342.0,
        508.0,
        618.0,
        647.0,
        745.0,
        726.0,
        622.0,
        467.0,
        271.0,
        74.0,
        0,
        0,
        0,
        0,
        0
      ],
      "last_updated": "2026-04-06 01:49 SAST",
      "last_hour": 0
    }
  },
  "thresholds": {
    "daily_avg": 425.7,
    "daily_min": 366.3,
    "pace_threshold_pct": 0.3,
    "sample_days": 4,
    "min_history_days": 7
  },
  "debug": {
    "reason": "nighttime",
    "sample_days": 4
  }
}