{
  "2026-03-25": {
    "total_kwh": 3222.43,
    "hourly": [
      0.0,
      0.0,
      0.0,
      0.0,
      0.0,
      0.0,
      0.0,
      21.66,
      173.34,
      345.19,
      156.6,
      467.49,
      501.16,
      494.73,
      445.53,
      341.79,
      215.35,
      59.59,
      0.0,
      0.0,
      0.0,
      0.0,
      0.0,
      0.0
    ],
    "irradiation": [
      0,
      0,
      0,
      0,
      0,
      0,
      0,
      17.0,
      113.0,
      285.0,
      546.0,
      706.0,
      764.0,
      727.0,
      707.0,
      652.0,
      511.0,
      275.0,
      107.0,
      4.0,
      0,
      0,
      0,
      0
    ],
    "last_updated": "2026-03-25 23:53 SAST",
    "last_hour": 17
  },
  "2026-03-26": {
    "total_kwh": 563.7,
    "hourly": [
      0.0,
      0.0,
      0.0,
      0.0,
      0.0,
      0.0,
      0.0,
      24.37,
      179.88,
      359.45,
      0.0,
      0.0,
      0.0,
      0.0,
      0.0,
      0.0,
      0.0,
      0.0,
      0.0,
      0.0,
      0.0,
      0.0,
      0.0,
      0.0
    ],
    "irradiation": [
      0,
      0,
      0,
      0,
      0,
      0,
      0,
      18.0,
      179.0,
      394.0,
      586.0,
      732.0,
      818.0,
      817.0,
      780.0,
      687.0,
      546.0,
      337.0,
      125.0,
      4.0,
      0,
      0,
      0,
      0
    ],
    "last_updated": "2026-03-26 09:26 SAST",
    "last_hour": 9
  }
}