{
  "plant": "WG Bloomingdales",
  "last_updated": "2026-04-15 21:26 SAST",
  "date": "2026-04-15",
  "total_kwh": 246.86,
  "last_hour": 18,
  "status": "ok",
  "alerts": {
    "offline": false,
    "pace_low": false,
    "total_low": false
  },
  "today": {
    "hourly_pv": [
      0.0,
      0.0,
      0.0,
      0.0,
      0.0,
      0.0,
      0.0,
      0.0,
      9.38,
      27.79,
      14.65,
      22.86,
      35.05,
      36.87,
      52.71,
      19.73,
      22.74,
      4.97,
      0.11,
      0.0,
      0.0,
      0.0,
      0.0,
      0.0
    ],
    "irradiation": [
      0,
      0,
      0,
      0,
      0,
      0,
      0,
      4.0,
      69.0,
      164.0,
      288.0,
      440.0,
      460.0,
      466.0,
      451.0,
      398.0,
      279.0,
      128.0,
      27.0,
      0,
      0,
      0,
      0,
      0
    ]
  },
  "hourly_pv": [
    0.0,
    0.0,
    0.0,
    0.0,
    0.0,
    0.0,
    0.0,
    0.0,
    9.38,
    27.79,
    14.65,
    22.86,
    35.05,
    36.87,
    52.71,
    19.73,
    22.74,
    4.97,
    0.11,
    0.0,
    0.0,
    0.0,
    0.0,
    0.0
  ],
  "irradiation": [
    0,
    0,
    0,
    0,
    0,
    0,
    0,
    4.0,
    69.0,
    164.0,
    288.0,
    440.0,
    460.0,
    466.0,
    451.0,
    398.0,
    279.0,
    128.0,
    27.0,
    0,
    0,
    0,
    0,
    0
  ],
  "stats_30day": {
    "hourly_avg": [
      0.0,
      0.0,
      0.0,
      0.0,
      0.0,
      0.0,
      0.0,
      0.06,
      1.62,
      16.26,
      25.68,
      31.5,
      26.8,
      30.82,
      28.69,
      25.34,
      15.9,
      5.6,
      0.13,
      0.0,
      0.0,
      0.0,
      0.0,
      0.0
    ],
    "hourly_min": [
      0,
      0,
      0,
      0,
      0,
      0,
      0,
      0.33,
      4.6,
      12.01,
      9.62,
      24.9,
      10.88,
      14.44,
      16.09,
      13.55,
      3.46,
      0.96,
      0.11,
      0,
      0,
      0,
      0,
      0
    ],
    "hourly_max": [
      0.0,
      0.0,
      0.0,
      0.0,
      0.0,
      0.0,
      0.0,
      0.33,
      5.1,
      31.31,
      48.86,
      58.47,
      51.31,
      51.35,
      44.77,
      36.99,
      23.28,
      10.11,
      0.24,
      0.0,
      0.0,
      0.0,
      0.0,
      0.0
    ],
    "hourly_p10": [
      0.0,
      0.0,
      0.0,
      0.0,
      0.0,
      0.0,
      0.0,
      0.0,
      0.0,
      0.0,
      4.81,
      12.45,
      5.44,
      7.22,
      8.04,
      6.78,
      4.97,
      1.96,
      0.11,
      0.0,
      0.0,
      0.0,
      0.0,
      0.0
    ],
    "hourly_p25": [
      0.0,
      0.0,
      0.0,
      0.0,
      0.0,
      0.0,
      0.0,
      0.0,
      0.0,
      3.0,
      11.76,
      25.52,
      13.31,
      16.33,
      17.87,
      18.43,
      9.84,
      3.2,
      0.11,
      0.0,
      0.0,
      0.0,
      0.0,
      0.0
    ],
    "hourly_p75": [
      0.0,
      0.0,
      0.0,
      0.0,
      0.0,
      0.0,
      0.0,
      0.0,
      3.45,
      27.24,
      39.47,
      41.54,
      44.15,
      48.69,
      44.27,
      34.32,
      21.41,
      7.97,
      0.11,
      0.0,
      0.0,
      0.0,
      0.0,
      0.0
    ],
    "hourly_p90": [
      0.0,
      0.0,
      0.0,
      0.0,
      0.0,
      0.0,
      0.0,
      0.17,
      4.85,
      29.34,
      44.54,
      51.21,
      50.3,
      50.09,
      44.64,
      35.71,
      22.48,
      9.12,
      0.17,
      0.0,
      0.0,
      0.0,
      0.0,
      0.0
    ],
    "hourly_irrad_avg": [
      0.0,
      0.0,
      0.0,
      0.0,
      0.0,
      0.0,
      0.0,
      4.0,
      81.5,
      194.7,
      302.5,
      411.5,
      498.0,
      528.2,
      478.0,
      419.3,
      279.5,
      154.5,
      37.5,
      0.0,
      0.0,
      0.0,
      0.0,
      0.0
    ],
    "daily_min": 9.6,
    "daily_max": 304.9,
    "daily_avg": 208.4,
    "sample_days": 6
  },
  "history": {
    "2026-04-09": {
      "total_kwh": 261.63,
      "hourly": [
        0.0,
        0.0,
        0.0,
        0.0,
        0.0,
        0.0,
        0.0,
        0.33,
        5.1,
        31.31,
        48.86,
        34.32,
        20.59,
        14.44,
        44.77,
        34.43,
        23.28,
        3.96,
        0.24,
        0.0,
        0.0,
        0.0,
        0.0,
        0.0
      ],
      "irradiation": [
        0,
        0,
        0,
        0,
        0,
        0,
        0,
        3.0,
        60.0,
        130.0,
        248.0,
        473.0,
        669.0,
        636.0,
        598.0,
        587.0,
        407.0,
        239.0,
        63.0,
        0,
        0,
        0,
        0,
        0
      ],
      "last_updated": "2026-04-09 23:57 SAST",
      "last_hour": 18
    },
    "2026-04-10": {
      "total_kwh": 262.1,
      "hourly": [
        0.0,
        0.0,
        0.0,
        0.0,
        0.0,
        0.0,
        0.0,
        0.0,
        0.0,
        27.38,
        40.22,
        24.9,
        28.71,
        48.82,
        23.19,
        36.99,
        21.67,
        10.11,
        0.11,
        0.0,
        0.0,
        0.0,
        0.0,
        0.0
      ],
      "irradiation": [
        0,
        0,
        0,
        0,
        0,
        0,
        0,
        7.0,
        130.0,
        272.0,
        372.0,
        500.0,
        577.0,
        655.0,
        567.0,
        554.0,
        326.0,
        200.0,
        56.0,
        0,
        0,
        0,
        0,
        0
      ],
      "last_updated": "2026-04-10 23:54 SAST",
      "last_hour": 18
    },
    "2026-04-11": {
      "total_kwh": 129.23,
      "hourly": [
        0.0,
        0.0,
        0.0,
        0.0,
        0.0,
        0.0,
        0.0,
        0.0,
        4.6,
        12.01,
        18.17,
        27.39,
        10.88,
        22.01,
        16.09,
        13.55,
        3.46,
        0.96,
        0.11,
        0.0,
        0.0,
        0.0,
        0.0,
        0.0
      ],
      "irradiation": [
        0,
        0,
        0,
        0,
        0,
        0,
        0,
        5.0,
        70.0,
        149.0,
        223.0,
        261.0,
        344.0,
        425.0,
        342.0,
        225.0,
        109.0,
        41.0,
        10.0,
        0,
        0,
        0,
        0,
        0
      ],
      "last_updated": "2026-04-11 23:48 SAST",
      "last_hour": 18
    },
    "2026-04-12": {
      "total_kwh": 9.55,
      "hourly": [
        0.0,
        0.0,
        0.0,
        0.0,
        0.0,
        0.0,
        0.0,
        0.0,
        0.0,
        0.0,
        0.0,
        0.0,
        0.0,
        0.0,
        0.0,
        0.0,
        6.49,
        2.95,
        0.11,
        0.0,
        0.0,
        0.0,
        0.0,
        0.0
      ],
      "irradiation": [
        0,
        0,
        0,
        0,
        0,
        0,
        0,
        0,
        0,
        0,
        0,
        0,
        0,
        0,
        0,
        0,
        0,
        0,
        0,
        0,
        0,
        0,
        0,
        0
      ],
      "last_updated": "2026-04-12 23:49 SAST",
      "last_hour": 18
    },
    "2026-04-13": {
      "total_kwh": 304.93,
      "hourly": [
        0.0,
        0.0,
        0.0,
        0.0,
        0.0,
        0.0,
        0.0,
        0.0,
        0.0,
        26.84,
        9.62,
        58.47,
        51.31,
        51.35,
        44.51,
        33.98,
        20.61,
        8.13,
        0.11,
        0.0,
        0.0,
        0.0,
        0.0,
        0.0
      ],
      "irradiation": [
        0,
        0,
        0,
        0,
        0,
        0,
        0,
        4.0,
        109.0,
        304.0,
        483.0,
        611.0,
        693.0,
        727.0,
        681.0,
        576.0,
        420.0,
        232.0,
        52.0,
        0,
        0,
        0,
        0,
        0
      ],
      "last_updated": "2026-04-13 23:08 SAST",
      "last_hour": 18
    },
    "2026-04-14": {
      "total_kwh": 282.81,
      "hourly": [
        0.0,
        0.0,
        0.0,
        0.0,
        0.0,
        0.0,
        0.0,
        0.0,
        0.0,
        0.0,
        37.2,
        43.95,
        49.3,
        48.28,
        43.55,
        33.07,
        19.88,
        7.47,
        0.11,
        0.0,
        0.0,
        0.0,
        0.0,
        0.0
      ],
      "irradiation": [
        0,
        0,
        0,
        0,
        0,
        0,
        0,
        5.0,
        120.0,
        313.0,
        489.0,
        624.0,
        705.0,
        726.0,
        680.0,
        574.0,
        415.0,
        215.0,
        44.0,
        0,
        0,
        0,
        0,
        0
      ],
      "last_updated": "2026-04-14 21:25 SAST",
      "last_hour": 18
    },
    "2026-04-15": {
      "total_kwh": 246.86,
      "hourly": [
        0.0,
        0.0,
        0.0,
        0.0,
        0.0,
        0.0,
        0.0,
        0.0,
        9.38,
        27.79,
        14.65,
        22.86,
        35.05,
        36.87,
        52.71,
        19.73,
        22.74,
        4.97,
        0.11,
        0.0,
        0.0,
        0.0,
        0.0,
        0.0
      ],
      "irradiation": [
        0,
        0,
        0,
        0,
        0,
        0,
        0,
        4.0,
        69.0,
        164.0,
        288.0,
        440.0,
        460.0,
        466.0,
        451.0,
        398.0,
        279.0,
        128.0,
        27.0,
        0,
        0,
        0,
        0,
        0
      ],
      "last_updated": "2026-04-15 21:26 SAST",
      "last_hour": 18
    }
  },
  "thresholds": {
    "daily_avg": 208.4,
    "daily_min": 9.6,
    "pace_threshold_pct": 0.3,
    "sample_days": 6,
    "min_history_days": 7
  },
  "debug": {
    "reason": "nighttime",
    "sample_days": 6
  }
}